final_osint-2.0.0.dist-info/licenses/LICENSE
finalosint/__init__.py
finalosint/main.py
final_osint-2.0.0.dist-info/METADATA
final_osint-2.0.0.dist-info/WHEEL
final_osint-2.0.0.dist-info/entry_points.txt
final_osint-2.0.0.dist-info/top_level.txt
final_osint-2.0.0.dist-info/RECORD
