Metadata-Version: 2.4
Name: final-osint
Version: 2.0.0
Summary: a powerful osint tool
Author-email: janz <tonmail@example.com>
License: MIT
Requires-Python: >=3.8
License-File: LICENSE
Dynamic: license-file
